README.md
pyproject.toml
device_discovery/__init__.py
device_discovery/client.py
device_discovery/defaults.py
device_discovery/discovery.py
device_discovery/interface.py
device_discovery/main.py
device_discovery/metrics.py
device_discovery/server.py
device_discovery/translate.py
device_discovery/version.py
device_discovery/policy/__init__.py
device_discovery/policy/manager.py
device_discovery/policy/models.py
device_discovery/policy/portscan.py
device_discovery/policy/runner.py
netboxlabs_device_discovery.egg-info/PKG-INFO
netboxlabs_device_discovery.egg-info/SOURCES.txt
netboxlabs_device_discovery.egg-info/dependency_links.txt
netboxlabs_device_discovery.egg-info/entry_points.txt
netboxlabs_device_discovery.egg-info/requires.txt
netboxlabs_device_discovery.egg-info/top_level.txt
tests/test_client.py
tests/test_defaults.py
tests/test_discovery.py
tests/test_interface.py
tests/test_main.py
tests/test_metrics.py
tests/test_server.py
tests/test_translate.py