Metadata-Version: 2.4
Name: netboxlabs-device-discovery
Version: 1.13.1
Summary: NetBox Labs, Device Discovery backend for Orb Agent, part of NetBox Discovery
Author-email: NetBox Labs <support@netboxlabs.com>
Maintainer-email: NetBox Labs <support@netboxlabs.com>
License: Apache-2.0
Project-URL: Homepage, https://netboxlabs.com/
Classifier: Development Status :: 3 - Alpha
Classifier: Intended Audience :: Developers
Classifier: Topic :: Software Development :: Build Tools
Classifier: License :: OSI Approved :: Apache Software License
Classifier: Programming Language :: Python :: 3
Classifier: Programming Language :: Python :: 3 :: Only
Classifier: Programming Language :: Python :: 3.10
Classifier: Programming Language :: Python :: 3.11
Classifier: Programming Language :: Python :: 3.12
Requires-Python: >=3.10
Requires-Dist: APScheduler~=3.10
Requires-Dist: croniter~=5.0
Requires-Dist: fastapi~=0.115
Requires-Dist: httpx~=0.27
Requires-Dist: napalm~=5.0
Requires-Dist: netboxlabs-diode-sdk~=1.9
Requires-Dist: pydantic~=2.9
Requires-Dist: python-dotenv~=1.0
Requires-Dist: uvicorn~=0.32
Requires-Dist: opentelemetry-api~=1.32
Requires-Dist: opentelemetry-sdk~=1.32
Requires-Dist: opentelemetry-exporter-otlp~=1.32
Provides-Extra: dev
Requires-Dist: black; extra == "dev"
Requires-Dist: check-manifest; extra == "dev"
Requires-Dist: ruff; extra == "dev"
Provides-Extra: test
Requires-Dist: coverage; extra == "test"
Requires-Dist: pytest; extra == "test"
Requires-Dist: pytest-cov==6.0.0; extra == "test"
